LICENSE
README.md
setup.py
chatinterface_server/__init__.py
chatinterface_server/dependencies.py
chatinterface_server/main.py
chatinterface_server/models.py
chatinterface_server/version.py
chatinterface_server/internal/__init__.py
chatinterface_server/internal/config.py
chatinterface_server/internal/database.py
chatinterface_server/routers/__init__.py
chatinterface_server/routers/auth.py
chatinterface_server/routers/chats.py
chatinterface_server/routers/ws.py
newguy103_chatinterface_server.egg-info/PKG-INFO
newguy103_chatinterface_server.egg-info/SOURCES.txt
newguy103_chatinterface_server.egg-info/dependency_links.txt
newguy103_chatinterface_server.egg-info/requires.txt
newguy103_chatinterface_server.egg-info/top_level.txt