Metadata-Version: 2.1
Name: newguy103-chatinterface-server
Version: 0.0.1
Summary: A simple centralized, self-hosted server for chatting.
Author: NewGuy103
Author-email: userchouenthusiast@gmail.com
License: GPL v2.0
License-File: LICENSE
Requires-Dist: msgpack
Requires-Dist: mysql-connector-python
Requires-Dist: fastapi
Requires-Dist: argon2-cffi
